Metadata-Version: 2.1
Name: pycord-ext-menus
Version: 1.0.0
Summary: An extension module to make reaction and button component menus with pycord
Home-page: https://github.com/PranoyMajumdar/pycord-ext-menus
Author: Pranoy#0140
License: Apache License
Project-URL: Bug Tracker, https://github.com/PranoyMajumdar/pycord-ext-menus
Requires-Python: >=3.8.0
Provides-Extra: docs
License-File: LICENSE
